{
  "updated_at": "2026-04-30T08:11:41.341042Z",
  "stories": [
    {
      "title": "Where the goblins came from",
      "score": 499
    },
    {
      "title": "Noctua releases official 3D CAD models for its cooling fans",
      "score": 170
    },
    {
      "title": "The Zig project's rationale for their firm anti-AI contribution policy",
      "score": 215
    },
    {
      "title": "Zed 1.0",
      "score": 1799
    },
    {
      "title": "Scott Aaronson on quantum: \"Will you heed my warnings NOW?\"",
      "score": 45
    }
  ]
}