{
  "updated_at": "2026-05-21T21:39:04.502471Z",
  "stories": [
    {
      "title": "Project Hail Mary \u2013 Stellar Navigation Chart",
      "score": 331
    },
    {
      "title": "Flipper One \u2013 we need your help",
      "score": 952
    },
    {
      "title": "Blog ran on Ubuntu 16.04 for 10 years. I migrated it to FreeBSD",
      "score": 66
    },
    {
      "title": "Show HN: Freenet, a peer-to-peer platform for decentralized apps",
      "score": 110
    },
    {
      "title": "Using Kagi Search with Low Vision",
      "score": 35
    }
  ]
}